figpy/__init__.py
figpy/proxlight.py
figpy-0.0.1.dist-info/METADATA
figpy-0.0.1.dist-info/WHEEL
figpy-0.0.1.dist-info/top_level.txt
figpy-0.0.1.dist-info/RECORD
