Metadata-Version: 2.1
Name: figpy
Version: 0.0.1
Summary: UNKNOWN
Home-page: UNKNOWN
Author: Pratyush Mishra
Author-email: proxlight02@gmail.com
License: MIT
Platform: UNKNOWN
Classifier: Programming Language :: Python :: 3
Classifier: License :: OSI Approved :: MIT License
Classifier: Operating System :: OS Independent
